InstaEncrypt/__init__.py
InstaEncrypt/decryption.py
InstaEncrypt/encryption.py
InstaEncrypt-1.0.dist-info/LICENSE
InstaEncrypt-1.0.dist-info/METADATA
InstaEncrypt-1.0.dist-info/WHEEL
InstaEncrypt-1.0.dist-info/top_level.txt
InstaEncrypt-1.0.dist-info/RECORD
