Metadata-Version: 2.1
Name: InstaEncrypt
Version: 1.0
Summary: Instantly Encrypts ur file
Home-page: https://github.com/rexdivakar/Fi1e-EncRypt0R
Author: Sanchit Jain, Divakar R
Author-email: sanchitjain1996@gmail.com, rexdivakar@hotmail.com
License: MIT
Keywords: AES Encryption System
Platform: UNKNOWN
Classifier: Development Status :: 5 - Production/Stable
Classifier: Intended Audience :: Education
Classifier: Operating System :: Microsoft :: Windows :: Windows 10
Classifier: License :: OSI Approved :: MIT License
Classifier: Programming Language :: Python :: 3
Requires-Dist: pyAesCrypt (==0.4.3)
Requires-Dist: rsa (==4.6)
